polars_timeseries-0.3.1.dist-info/METADATA
polars_timeseries-0.3.1.dist-info/WHEEL
polars_ts/__init__.py
polars_ts/decomposition/__init__.py
polars_ts/decomposition/fourier_decomposition.py
polars_ts/decomposition/seasonal_decompose_features.py
polars_ts/decomposition/seasonal_decomposition.py
polars_ts/metrics/__init__.py
polars_ts/metrics/kaboudan.py
polars_ts/models/__init__.py
polars_ts/models/scum.py
polars_ts_rs/__init__.py
polars_ts_rs/polars_ts_rs.abi3.so
polars_timeseries-0.3.1.dist-info/RECORD
