Metadata-Version: 2.4
Name: polars-timeseries
Version: 0.3.1
Requires-Dist: polars>=1.20.0
Requires-Dist: iprogress>=0.4
Requires-Dist: loguru>=0.7.3
Requires-Dist: statsforecast>=2.0.0
Requires-Dist: pyarrow>=19.0.0
Requires-Dist: maturin>=1.8.1
Requires-Dist: polars-ds>=0.7.0
Requires-Dist: statsmodels>=0.14.4
Summary: Polars Time Series Extension
Author: Torben Windler
Requires-Python: >=3.12, <3.13
Project-URL: Source, https://github.com/drumtorben/polars-ts.git
